alphaturtle/alphaturtle.py
alphaturtle/alphaturtle_cli.py
alphaturtle/alphaturtle_gui.py
alphaturtle-1.2.dist-info/LICENSE.txt
alphaturtle-1.2.dist-info/METADATA
alphaturtle-1.2.dist-info/WHEEL
alphaturtle-1.2.dist-info/entry_points.txt
alphaturtle-1.2.dist-info/top_level.txt
alphaturtle-1.2.dist-info/RECORD
