Metadata-Version: 2.1
Name: alphaturtle
Version: 1.2
Summary: To Draw Alphabet And Number Using Turtle Module
Home-page: https://github.com/C0DE-SLAYER/alphaturtle
Author: Faisal Ali Sayyed
Author-email: fsali315@gmail.com
License: MIT
Platform: UNKNOWN
Classifier: License :: OSI Approved :: MIT License
Classifier: Programming Language :: Python :: 3
